xontrib/ergopack.py
xontrib_ergopack-0.2.0.dist-info/LICENSE
xontrib_ergopack-0.2.0.dist-info/METADATA
xontrib_ergopack-0.2.0.dist-info/WHEEL
xontrib_ergopack-0.2.0.dist-info/top_level.txt
xontrib_ergopack-0.2.0.dist-info/RECORD
