Metadata-Version: 2.1
Name: xontrib-ergopack
Version: 0.2.0
Summary: Meta package that installs group of ergonomic xontribs in xonsh shell.
Home-page: https://github.com/anki-code/xontrib-ergopack
Author: anki-code
Author-email: no@no.no
License: MIT
Project-URL: Documentation, https://github.com/anki-code/xontrib-ergopack/blob/master/README.md
Project-URL: Code, https://github.com/anki-code/xontrib-ergopack
Project-URL: Issue tracker, https://github.com/anki-code/xontrib-ergopack/issues
Platform: any
Classifier: Programming Language :: Python :: 3
Classifier: Programming Language :: Python :: 3.6
Classifier: Programming Language :: Python :: 3.7
Classifier: Programming Language :: Python :: 3.8
Classifier: License :: OSI Approved :: MIT License
Classifier: Operating System :: OS Independent
Classifier: Topic :: System :: Shells
Classifier: Topic :: System :: System Shells
Classifier: Topic :: Terminals
Requires-Python: >=3.6
License-File: LICENSE
Requires-Dist: xontrib-argcomplete
Requires-Dist: xontrib-back2dir
Requires-Dist: xontrib-output-search
Requires-Dist: xontrib-pipeliner
Requires-Dist: xontrib-sh
Requires-Dist: xonsh-autoxsh
Requires-Dist: xontrib-history-encrypt
Requires-Dist: xontrib-clp
Requires-Dist: xontrib-cmd-durations
Provides-Extra: dev
Requires-Dist: xontrib-macro ; extra == 'dev'
Requires-Dist: xontrib-debug-tools ; extra == 'dev'
Requires-Dist: xontrib-hist-format ; extra == 'dev'
Requires-Dist: xontrib-readable-traceback ; extra == 'dev'
Requires-Dist: hunter ; extra == 'dev'
Provides-Extra: onepath
Requires-Dist: xontrib-onepath ; extra == 'onepath'
Provides-Extra: prompt
Requires-Dist: xontrib-prompt-bar ; extra == 'prompt'
Requires-Dist: xontrib-prompt-starship ; extra == 'prompt'
